code_retreat/__init__.py
code_retreat/__main__.py
code_retreat/server.py
code_retreat/testing.py
jsox_code_retreat-0.6.0.dist-info/DESCRIPTION.rst
jsox_code_retreat-0.6.0.dist-info/entry_points.txt
jsox_code_retreat-0.6.0.dist-info/METADATA
jsox_code_retreat-0.6.0.dist-info/metadata.json
jsox_code_retreat-0.6.0.dist-info/RECORD
jsox_code_retreat-0.6.0.dist-info/top_level.txt
jsox_code_retreat-0.6.0.dist-info/WHEEL
