Metadata-Version: 2.0
Name: jsox-code-retreat
Version: 0.6.0
Summary: Python Runner for JS Oxford's Code Retreat
Home-page: http://github.com/jsoxford/code-retreat-py
Author: George Hickman
Author-email: george@ghickman.co.uk
License: MIT
Platform: UNKNOWN
Classifier: Development Status :: 5 - Production/Stable
Classifier: Environment :: Console
Classifier: License :: OSI Approved :: MIT License
Classifier: Operating System :: MacOS :: MacOS X
Classifier: Operating System :: POSIX :: Linux
Classifier: Programming Language :: Python :: 2
Classifier: Programming Language :: Python :: 2.7
Classifier: Programming Language :: Python :: 3
Classifier: Programming Language :: Python :: 3.4
Requires-Dist: pytest (==2.5.2)
Requires-Dist: requests (==2.3.0)
